_gappedbuf.cpython-312-darwin.so
gappedbuf/__init__.py
gappedbuf/re.py
gappedbuf/sre_compile.py
gappedbuf/sre_constants.py
gappedbuf/sre_parse.py
kaa/__init__.py
kaa/addon.py
kaa/clipboard.py
kaa/command.py
kaa/config.py
kaa/consts.py
kaa/context.py
kaa/cursor.py
kaa/doc_re.py
kaa/document.py
kaa/editmode.py
kaa/encodingdef.py
kaa/exceptions.py
kaa/fileio.py
kaa/keyboard.py
kaa/log.py
kaa/macro.py
kaa/options.py
kaa/screen.py
kaa/syntax_highlight.py
kaa/theme.py
kaa/tools.py
kaa/utils.py
kaa/version.py
kaa/commands/__init__.py
kaa/commands/appcommand.py
kaa/commands/editmodecommand.py
kaa/commands/editorcommand.py
kaa/commands/filecommand.py
kaa/commands/gitcommand.py
kaa/commands/toolcommand.py
kaa/commands/vicommand.py
kaa/cui/__init__.py
kaa/cui/app.py
kaa/cui/color.py
kaa/cui/dialog.py
kaa/cui/editor.py
kaa/cui/frame.py
kaa/cui/keydef.py
kaa/cui/main.py
kaa/cui/splitter.py
kaa/cui/wnd.py
kaa/filetype/__init__.py
kaa/filetype/filetypedef.py
kaa/filetype/c/__init__.py
kaa/filetype/c/cmode.py
kaa/filetype/css/__init__.py
kaa/filetype/css/cssmode.py
kaa/filetype/default/__init__.py
kaa/filetype/default/defaultmode.py
kaa/filetype/default/keybind.py
kaa/filetype/default/menu.py
kaa/filetype/default/modebase.py
kaa/filetype/default/theme.py
kaa/filetype/diff/__init__.py
kaa/filetype/diff/diffmode.py
kaa/filetype/html/__init__.py
kaa/filetype/html/htmlmode.py
kaa/filetype/ini/__init__.py
kaa/filetype/ini/inimode.py
kaa/filetype/javascript/__init__.py
kaa/filetype/javascript/javascriptmode.py
kaa/filetype/json/__init__.py
kaa/filetype/json/jsonmode.py
kaa/filetype/markdown/__init__.py
kaa/filetype/markdown/markdownmode.py
kaa/filetype/python/__init__.py
kaa/filetype/python/pythonmode.py
kaa/filetype/rst/__init__.py
kaa/filetype/rst/rstmode.py
kaa/ui/__init__.py
kaa/ui/dialog/__init__.py
kaa/ui/dialog/dialogmode.py
kaa/ui/fileinfo/__init__.py
kaa/ui/fileinfo/fileinfomode.py
kaa/ui/filenameindex/__init__.py
kaa/ui/filenameindex/filenameindexmode.py
kaa/ui/git/__init__.py
kaaedit-0.54.1.dist-info/METADATA
kaaedit-0.54.1.dist-info/WHEEL
kaaedit-0.54.1.dist-info/entry_points.txt
kaaedit-0.54.1.dist-info/top_level.txt
kaaedit-0.54.1.dist-info/RECORD
