Metadata-Version: 2.1
Name: kaaedit
Version: 0.54.1
Summary: kaa - console text editor.
Home-page: https://github.com/kaaedit/kaa
Author: Atsuo Ishimoto
Author-email: ishimoto@gembook.org
License: MIT License
Classifier: Programming Language :: Python :: 3
Classifier: Development Status :: 3 - Alpha
Classifier: Topic :: Text Editors
Classifier: Topic :: Software Development :: Debuggers
Classifier: Environment :: Console :: Curses
Classifier: License :: OSI Approved :: MIT License
Requires-Dist: curses-ex
Requires-Dist: pyjf3
Requires-Dist: setproctitle
Requires-Dist: gitpython
Requires-Dist: kaadbg >=0.3.0
